{"route_id": 66, "direction": "one-direction", "station": [{"stop_name": "\u0110\u1ea1i h\u1ecdc Qu\u1ed1c t\u1ebf Mi\u1ec1n \u0110\u00f4ng", "time": [{"off_dates": "T7,CN", "stop_time": "07:34:00"}, {"off_dates": "T7,CN", "stop_time": "08:04:00"}, {"off_dates": "T7,CN", "stop_time": "08:34:00"}, {"off_dates": "T7,CN", "stop_time": "09:04:00"}, {"off_dates": "CN", "stop_time": "11:04:00"}, {"off_dates": "CN", "stop_time": "11:34:00"}, {"off_dates": "CN", "stop_time": "12:04:00"}, {"off_dates": "CN", "stop_time": "12:34:00"}, {"off_dates": "T7,CN", "stop_time": "15:04:00"}, {"off_dates": "T7,CN", "stop_time": "15:34:00"}, {"off_dates": "T7,CN", "stop_time": "16:04:00"}]}, {"stop_name": "C\u1ed5ng B\u0103\u0301c \u0110\u1ea1i h\u1ecdc Qu\u1ed1c t\u1ebf Mi\u1ec1n \u0110\u00f4ng", "time": [{"off_dates": "T7,CN", "stop_time": "07:35:00"}, {"off_dates": "T7,CN", "stop_time": "08:05:00"}, {"off_dates": "T7,CN", "stop_time": "08:35:00"}, {"off_dates": "T7,CN", "stop_time": "09:05:00"}, {"off_dates": "CN", "stop_time": "11:05:00"}, {"off_dates": "CN", "stop_time": "11:35:00"}, {"off_dates": "CN", "stop_time": "12:05:00"}, {"off_dates": "CN", "stop_time": "12:35:00"}, {"off_dates": "T7,CN", "stop_time": "15:05:00"}, {"off_dates": "T7,CN", "stop_time": "15:35:00"}, {"off_dates": "T7,CN", "stop_time": "16:05:00"}]}, {"stop_name": "Becamex UDJ Lake View", "time": [{"off_dates": "T7,CN", "stop_time": "07:38:00"}, {"off_dates": "T7,CN", "stop_time": "08:08:00"}, {"off_dates": "T7,CN", "stop_time": "08:38:00"}, {"off_dates": "T7,CN", "stop_time": "09:08:00"}, {"off_dates": "CN", "stop_time": "11:08:00"}, {"off_dates": "CN", "stop_time": "11:38:00"}, {"off_dates": "CN", "stop_time": "12:08:00"}, {"off_dates": "CN", "stop_time": "12:38:00"}, {"off_dates": "T7,CN", "stop_time": "15:08:00"}, {"off_dates": "T7,CN", "stop_time": "15:38:00"}, {"off_dates": "T7,CN", "stop_time": "16:08:00"}]}, {"stop_name": "C\u00f4ng vi\u00ean trung t\u00e2m Th\u00e0nh ph\u1ed1 M\u1edbi BD", "time": [{"off_dates": "T7,CN", "stop_time": "07:39:00"}, {"off_dates": "T7,CN", "stop_time": "08:09:00"}, {"off_dates": "T7,CN", "stop_time": "08:39:00"}, {"off_dates": "T7,CN", "stop_time": "09:09:00"}, {"off_dates": "CN", "stop_time": "11:09:00"}, {"off_dates": "CN", "stop_time": "11:39:00"}, {"off_dates": "CN", "stop_time": "12:09:00"}, {"off_dates": "CN", "stop_time": "12:39:00"}, {"off_dates": "T7,CN", "stop_time": "15:09:00"}, {"off_dates": "T7,CN", "stop_time": "15:39:00"}, {"off_dates": "T7,CN", "stop_time": "16:09:00"}]}, {"stop_name": "Trung t\u00e2m th\u1ec3 thao Th\u00e0nh ph\u1ed1 M\u1edbi BD", "time": [{"off_dates": "T7,CN", "stop_time": "07:41:00"}, {"off_dates": "T7,CN", "stop_time": "08:11:00"}, {"off_dates": "T7,CN", "stop_time": "08:41:00"}, {"off_dates": "T7,CN", "stop_time": "09:11:00"}, {"off_dates": "CN", "stop_time": "11:11:00"}, {"off_dates": "CN", "stop_time": "11:41:00"}, {"off_dates": "CN", "stop_time": "12:11:00"}, {"off_dates": "CN", "stop_time": "12:41:00"}, {"off_dates": "T7,CN", "stop_time": "15:11:00"}, {"off_dates": "T7,CN", "stop_time": "15:41:00"}, {"off_dates": "T7,CN", "stop_time": "16:11:00"}]}, {"stop_name": "C\u00f4ng ty Becamex Tokyu", "time": [{"off_dates": "T7,CN", "stop_time": "07:41:00"}, {"off_dates": "T7,CN", "stop_time": "08:11:00"}, {"off_dates": "T7,CN", "stop_time": "08:41:00"}, {"off_dates": "T7,CN", "stop_time": "09:11:00"}, {"off_dates": "CN", "stop_time": "11:11:00"}, {"off_dates": "CN", "stop_time": "11:41:00"}, {"off_dates": "CN", "stop_time": "12:11:00"}, {"off_dates": "CN", "stop_time": "12:41:00"}, {"off_dates": "T7,CN", "stop_time": "15:11:00"}, {"off_dates": "T7,CN", "stop_time": "15:41:00"}, {"off_dates": "T7,CN", "stop_time": "16:11:00"}]}, {"stop_name": "SORA gardens", "time": [{"off_dates": "T7,CN", "stop_time": "07:43:00"}, {"off_dates": "T7,CN", "stop_time": "08:13:00"}, {"off_dates": "T7,CN", "stop_time": "08:43:00"}, {"off_dates": "T7,CN", "stop_time": "09:13:00"}, {"off_dates": "CN", "stop_time": "11:13:00"}, {"off_dates": "CN", "stop_time": "11:43:00"}, {"off_dates": "CN", "stop_time": "12:13:00"}, {"off_dates": "CN", "stop_time": "12:43:00"}, {"off_dates": "T7,CN", "stop_time": "15:13:00"}, {"off_dates": "T7,CN", "stop_time": "15:43:00"}, {"off_dates": "T7,CN", "stop_time": "16:13:00"}]}, {"stop_name": "Lucky Square", "time": [{"off_dates": "T7,CN", "stop_time": "07:44:00"}, {"off_dates": "T7,CN", "stop_time": "08:14:00"}, {"off_dates": "T7,CN", "stop_time": "08:44:00"}, {"off_dates": "T7,CN", "stop_time": "09:14:00"}, {"off_dates": "CN", "stop_time": "11:14:00"}, {"off_dates": "CN", "stop_time": "11:44:00"}, {"off_dates": "CN", "stop_time": "12:14:00"}, {"off_dates": "CN", "stop_time": "12:44:00"}, {"off_dates": "T7,CN", "stop_time": "15:14:00"}, {"off_dates": "T7,CN", "stop_time": "15:44:00"}, {"off_dates": "T7,CN", "stop_time": "16:14:00"}]}, {"stop_name": "Ph\u00f4\u0301 Th\u01b0\u01a1ng ma\u0323i - L\u00ea L\u01a1\u0323i", "time": [{"off_dates": "T7,CN", "stop_time": "07:45:00"}, {"off_dates": "T7,CN", "stop_time": "08:15:00"}, {"off_dates": "T7,CN", "stop_time": "08:45:00"}, {"off_dates": "T7,CN", "stop_time": "09:15:00"}, {"off_dates": "CN", "stop_time": "11:15:00"}, {"off_dates": "CN", "stop_time": "11:45:00"}, {"off_dates": "CN", "stop_time": "12:15:00"}, {"off_dates": "CN", "stop_time": "12:45:00"}, {"off_dates": "T7,CN", "stop_time": "15:15:00"}, {"off_dates": "T7,CN", "stop_time": "15:45:00"}, {"off_dates": "T7,CN", "stop_time": "16:15:00"}]}, {"stop_name": "Ph\u00f4\u0301 Th\u01b0\u01a1ng ma\u0323i - \u0110\u1ed3ng Kh\u1edfi", "time": [{"off_dates": "T7,CN", "stop_time": "07:46:00"}, {"off_dates": "T7,CN", "stop_time": "08:16:00"}, {"off_dates": "T7,CN", "stop_time": "08:46:00"}, {"off_dates": "T7,CN", "stop_time": "09:16:00"}, {"off_dates": "CN", "stop_time": "11:16:00"}, {"off_dates": "CN", "stop_time": "11:46:00"}, {"off_dates": "CN", "stop_time": "12:16:00"}, {"off_dates": "CN", "stop_time": "12:46:00"}, {"off_dates": "T7,CN", "stop_time": "15:16:00"}, {"off_dates": "T7,CN", "stop_time": "15:46:00"}, {"off_dates": "T7,CN", "stop_time": "16:16:00"}]}, {"stop_name": "Ph\u00f4\u0301 Th\u01b0\u01a1ng ma\u0323i - L\u00fd Th\u00e1i T\u1ed5", "time": [{"off_dates": "T7,CN", "stop_time": "07:47:00"}, {"off_dates": "T7,CN", "stop_time": "08:17:00"}, {"off_dates": "T7,CN", "stop_time": "08:47:00"}, {"off_dates": "T7,CN", "stop_time": "09:17:00"}, {"off_dates": "CN", "stop_time": "11:17:00"}, {"off_dates": "CN", "stop_time": "11:47:00"}, {"off_dates": "CN", "stop_time": "12:17:00"}, {"off_dates": "CN", "stop_time": "12:47:00"}, {"off_dates": "T7,CN", "stop_time": "15:17:00"}, {"off_dates": "T7,CN", "stop_time": "15:47:00"}, {"off_dates": "T7,CN", "stop_time": "16:17:00"}]}, {"stop_name": "Kh\u00e1ch s\u1ea1n Becamex Th\u00e0nh ph\u1ed1 M\u1edbi", "time": [{"off_dates": "T7,CN", "stop_time": "07:48:00"}, {"off_dates": "T7,CN", "stop_time": "08:18:00"}, {"off_dates": "T7,CN", "stop_time": "08:48:00"}, {"off_dates": "T7,CN", "stop_time": "09:18:00"}, {"off_dates": "CN", "stop_time": "11:18:00"}, {"off_dates": "CN", "stop_time": "11:48:00"}, {"off_dates": "CN", "stop_time": "12:18:00"}, {"off_dates": "CN", "stop_time": "12:48:00"}, {"off_dates": "T7,CN", "stop_time": "15:18:00"}, {"off_dates": "T7,CN", "stop_time": "15:48:00"}, {"off_dates": "T7,CN", "stop_time": "16:18:00"}]}, {"stop_name": "hikari", "time": [{"off_dates": "T7,CN", "stop_time": "07:50:00"}, {"off_dates": "T7,CN", "stop_time": "08:20:00"}, {"off_dates": "T7,CN", "stop_time": "08:50:00"}, {"off_dates": "T7,CN", "stop_time": "09:20:00"}, {"off_dates": "CN", "stop_time": "11:20:00"}, {"off_dates": "CN", "stop_time": "11:50:00"}, {"off_dates": "CN", "stop_time": "12:20:00"}, {"off_dates": "CN", "stop_time": "12:50:00"}, {"off_dates": "T7,CN", "stop_time": "15:20:00"}, {"off_dates": "T7,CN", "stop_time": "15:50:00"}, {"off_dates": "T7,CN", "stop_time": "16:20:00"}]}, {"stop_name": "B\u1ea3o hi\u1ec3m x\u00e3 h\u1ed9i t\u1ec9nh B\u00ecnh D\u01b0\u01a1ng", "time": [{"off_dates": "T7,CN", "stop_time": "07:50:00"}, {"off_dates": "T7,CN", "stop_time": "08:20:00"}, {"off_dates": "T7,CN", "stop_time": "08:50:00"}, {"off_dates": "T7,CN", "stop_time": "09:20:00"}, {"off_dates": "CN", "stop_time": "11:20:00"}, {"off_dates": "CN", "stop_time": "11:50:00"}, {"off_dates": "CN", "stop_time": "12:20:00"}, {"off_dates": "CN", "stop_time": "12:50:00"}, {"off_dates": "T7,CN", "stop_time": "15:20:00"}, {"off_dates": "T7,CN", "stop_time": "15:50:00"}, {"off_dates": "T7,CN", "stop_time": "16:20:00"}]}, {"stop_name": "Aroma - L\u00ea Lai", "time": [{"off_dates": "T7,CN", "stop_time": "07:52:00"}, {"off_dates": "T7,CN", "stop_time": "08:22:00"}, {"off_dates": "T7,CN", "stop_time": "08:52:00"}, {"off_dates": "T7,CN", "stop_time": "09:22:00"}, {"off_dates": "CN", "stop_time": "11:22:00"}, {"off_dates": "CN", "stop_time": "11:52:00"}, {"off_dates": "CN", "stop_time": "12:22:00"}, {"off_dates": "CN", "stop_time": "12:52:00"}, {"off_dates": "T7,CN", "stop_time": "15:22:00"}, {"off_dates": "T7,CN", "stop_time": "15:52:00"}, {"off_dates": "T7,CN", "stop_time": "16:22:00"}]}, {"stop_name": "\u0110\u1ea1i h\u1ecdc Qu\u1ed1c t\u1ebf Mi\u1ec1n \u0110\u00f4ng", "time": [{"off_dates": "T7,CN", "stop_time": "07:57:00"}, {"off_dates": "T7,CN", "stop_time": "08:27:00"}, {"off_dates": "T7,CN", "stop_time": "08:57:00"}, {"off_dates": "T7,CN", "stop_time": "09:27:00"}, {"off_dates": "CN", "stop_time": "11:27:00"}, {"off_dates": "CN", "stop_time": "11:57:00"}, {"off_dates": "CN", "stop_time": "12:27:00"}, {"off_dates": "CN", "stop_time": "12:57:00"}, {"off_dates": "T7,CN", "stop_time": "15:27:00"}, {"off_dates": "T7,CN", "stop_time": "15:57:00"}, {"off_dates": "T7,CN", "stop_time": "16:27:00"}]}]}